README.rst
setup.cfg
setup.py
pymls/__init__.py
pymls/analysis.py
pymls/backing.py
pymls/solver.py
pymls/interface/__init__.py
pymls/interface/interfaces.py
pymls/interface/interfaces_rigid.py
pymls/interface/utils.py
pymls/layers/__init__.py
pymls/layers/elastic.py
pymls/layers/fluid.py
pymls/layers/layer.py
pymls/layers/pem.py
pymls/layers/screen.py
pymls/layers/utils.py
pymls/media/__init__.py
pymls/media/air.py
pymls/media/elastic.py
pymls/media/eqf.py
pymls/media/fluid.py
pymls/media/medium.py
pymls/media/pem.py
pymls/media/screen.py
pymls/utils/__init__.py
pymls/utils/draws_manager.py
pymls/utils/hdf5_export.py
pymls/utils/indicators.py
pymlslecture.egg-info/PKG-INFO
pymlslecture.egg-info/SOURCES.txt
pymlslecture.egg-info/dependency_links.txt
pymlslecture.egg-info/not-zip-safe
pymlslecture.egg-info/requires.txt
pymlslecture.egg-info/top_level.txt
tests/__init__.py
tests/test_media_loading.py
tests/test_solver.py