Metadata-Version: 2.1
Name: pymlslecture
Version: 0.0.1
Summary: Acoustic multilayer solver in Python
Home-page: https://github.com/cpplanes/pymls
Author: O. Dazel, Mathieu (matael) Gaborit, P. Göransson
Author-email: gaborit@kth.se
License: MIT
Platform: UNKNOWN
Classifier: Programming Language :: Python :: 3
Classifier: Operating System :: OS Independent
Provides-Extra: HDF5 export
